{
  "achievements": [
    {
      "title": "January 2023",
      "cardTitle": "AWS Cloud Quest: Cloud Practitioner",
      "cardSubtitle": "Amazon Web Services (AWS Training & Certificaton)",
      "cardDetailedText": [
        "Earners of this badge have demonstrated basic solution building knowledge using AWS services and have a fundamental understanding of AWS Cloud concepts.",
        "Badge earners have acquired hands-on experience with compute, networking, database and security services."
      ],
      "media": {
        "type": "IMAGE",
        "source": {
          "url": "/images/achievements/Phani_AWSCloud_Quest_CredlyBadge.png"
        }
      }
    },
    {
      "title": "December 2022",
      "cardTitle": "Product-Led Certified",
      "cardSubtitle": "Pend & Mind The Product",
      "cardDetailedText": [
        "Earners of this badge have demonstrated their knowledge of how to place their product at the center of the customer experience.",
        "Leverage their product to solve challenges across all departments of the business, thereby being product led."
      ],
      "media": {
        "type": "IMAGE",
        "source": {
          "url": "/images/achievements/PhaniM_ProductLed_Certified.png"
        }
      }
    },
    {
      "title": "May 2021",
      "cardTitle": "Bravo Award",
      "cardSubtitle": "Walmart Global Tech India",
      "cardDetailedText": [
        "For developing the Enterprise Service Bus (ESB) carrying 40+ interfaces of real-time data for Walmart Fulfillment Services (WFS)",
        "Enabling the 2-Day Delivery across the Nationwide of USA by saving $60B"
      ],
      "media": {
        "type": "IMAGE",
        "source": {
          "url": "/images/achievements/phani_bravo_award.png"
        }
      }
    },
    {
      "title": "June 2021",
      "cardTitle": "Innovation Award",
      "cardSubtitle": "Walmart Global Tech India",
      "cardDetailedText": "For creating Python scripts to handle 2 million records in seconds instead of the traditional way.",
      "media": {
        "type": "IMAGE",
        "source": {
          "url": "/images/achievements/phani_innovation_award.png"
        }
      }
    },
    {
      "title": "July 2018",
      "cardTitle": "Brighter Blue",
      "cardSubtitle": "IBM India Pvt Ltd",
      "cardDetailedText": [
        "For creating a Google Assistant that conversed as my friend during my speech.",
        "Everyone had a great time and I was appreciated for my ability to utilize technology for conveying engaging stories."
      ],
      "media": {
        "type": "IMAGE",
        "source": {
          "url": "/images/achievements/phani_ibm_award.jpg"
        }
      }
    },
    {
      "title": "April 2017",
      "cardTitle": "College Representative Recognition",
      "cardSubtitle": "Entrepreneurship Cell of IIT Bombay",
      "cardDetailedText": [
        "For representing my college in collecting innovative ideas from students.",
        "For creating the spirit of Entrepreneurship within the young minds by driving the community."
      ],
      "media": {
        "type": "IMAGE",
        "source": {
          "url": "/images/achievements/phani_iit_bombay.jpg"
        }
      }
    },
    {
      "title": "December 2016",
      "cardTitle": "3rd Place 24 Hour Code-A-Thon",
      "cardSubtitle": "Miracle Software Systems, Inc",
      "cardDetailedText": "Achieved 3rd place in the segment of Internet of Things concept in the time of 24hours continous coding to build a working application.",
      "media": {
        "type": "IMAGE",
        "source": {
          "url": "/images/achievements/phani_miracle.jpg"
        }
      }
    },
    {
      "title": "Aug 2016",
      "cardTitle": "2nd Place at National Level Project Presentation",
      "cardSubtitle": "Jawaharlal Nehru Technological University, Kakinada (JNTUK)",
      "cardDetailedText": [
        "Achieved 2nd place in both project competition held by JNTUK at national level.",
        "Project presentation was on the e-Magazine which I created as a platform for entire student body in the college."
      ],
      "media": {
        "type": "IMAGE",
        "source": {
          "url": "/images/achievements/phani_jntuk_project.jpg"
        }
      }
    },
    {
      "title": "Aug 2016",
      "cardTitle": "2nd Place at National Level Paper Presentation",
      "cardSubtitle": "Jawaharlal Nehru Technological University, Kakinada (JNTUK)",
      "cardDetailedText": [
        "Achieved 2nd place in paper presentations competitions held by JNTUK at national level.",
        "There were total 202 teams participated on different Computer Science topics and I have presented The Human IQ vs AI."
      ],
      "media": {
        "type": "IMAGE",
        "source": {
          "url": "/images/achievements/phani_jntuk_paper.jpg"
        }
      }
    }
  ]
}
